redditimage/__init__.py
redditimage/compact_image.py
redditimage/redditimage.py
redditimage/models/__init__.py
redditimage/models/positioned_image.py
redditimage/models/relative_position.py
redditimage/models/vote.py
redditimage/utils/__init__.py
redditimage/utils/pil_utils.py
redditimage/utils/reddit_image_utils.py
redditimage-0.0.15.dist-info/METADATA
redditimage-0.0.15.dist-info/WHEEL
redditimage-0.0.15.dist-info/top_level.txt
redditimage-0.0.15.dist-info/RECORD
