Metadata-Version: 2.1
Name: redditimage
Version: 0.0.15
Summary: redditimage
Home-page: https://github.com/kkristof200/py_reddit_image
Author: Kristof
License: UNKNOWN
Platform: UNKNOWN
Classifier: Programming Language :: Python :: 3
Classifier: License :: OSI Approved :: MIT License
Classifier: Operating System :: OS Independent
Requires-Python: >=3.5
Requires-Dist: colorthief
Requires-Dist: Pillow
